pyramid_letsencrypt/__init__.py
pyramid_letsencrypt/letsencrypt.py
pyramid_letsencrypt/nose_fix.py
pyramid_letsencrypt-0.1.dist-info/DESCRIPTION.rst
pyramid_letsencrypt-0.1.dist-info/METADATA
pyramid_letsencrypt-0.1.dist-info/RECORD
pyramid_letsencrypt-0.1.dist-info/WHEEL
pyramid_letsencrypt-0.1.dist-info/metadata.json
pyramid_letsencrypt-0.1.dist-info/top_level.txt
