Metadata-Version: 2.0
Name: pyramid-letsencrypt
Version: 0.1
Summary: A package which provides an easy way to host Let's Encrypt domain validation content in your Pyramid project.
Home-page: https://github.com/niteoweb/pyramid_letsencrypt
Author: NiteoWeb Ltd.
Author-email: info@niteoweb.com
License: BSD
Keywords: wsgi pylons pyramid ssl letsencrypt
Platform: UNKNOWN
Classifier: Intended Audience :: Developers
Classifier: Programming Language :: Python
Classifier: Programming Language :: Python :: 2.7
Classifier: Programming Language :: Python :: 3
Classifier: Programming Language :: Python :: 3.5
Classifier: Framework :: Pyramid
Classifier: Topic :: Internet :: WWW/HTTP :: WSGI
Classifier: License :: OSI Approved :: BSD License
Requires-Dist: pyramid (>=1.4)
Provides-Extra: testing
Requires-Dist: WebTest; extra == 'testing'
Requires-Dist: coverage; extra == 'testing'
Requires-Dist: nose; extra == 'testing'
